bigcode_embeddings/__init__.py
bigcode_embeddings/__main__.py
bigcode_embeddings/cli.py
bigcode_embeddings/model_utils.py
bigcode_embeddings/visualization.py
bigcode_embeddings/word2vec.py
bigcode_embeddings-0.1.2.data/scripts/bigcode-embeddings
bigcode_embeddings-0.1.2.dist-info/DESCRIPTION.rst
bigcode_embeddings-0.1.2.dist-info/METADATA
bigcode_embeddings-0.1.2.dist-info/RECORD
bigcode_embeddings-0.1.2.dist-info/WHEEL
bigcode_embeddings-0.1.2.dist-info/metadata.json
bigcode_embeddings-0.1.2.dist-info/top_level.txt
bigcode_embeddings-0.1.2.dist-info/zip-safe
