Metadata-Version: 2.0
Name: bigcode-embeddings
Version: 0.1.2
Summary: Tool generate and visualize embeddings from bigcode
Home-page: https://github.com/tuvistavie/bigcode-tools/tree/master/bigcode-embeddings
Author: Daniel Perez
Author-email: tuvistavie@gmail.com
License: UNKNOWN
Download-URL: https://github.com/tuvistavie/bigcode-tools/archive/master.zip
Platform: UNKNOWN
Classifier: Development Status :: 4 - Beta
Classifier: Intended Audience :: Developers
Classifier: License :: OSI Approved :: MIT License
Classifier: Operating System :: OS Independent
Classifier: Programming Language :: Python :: 3
Requires-Dist: pandas
Requires-Dist: scipy
Requires-Dist: numpy
Requires-Dist: scikit-learn
Requires-Dist: matplotlib
Requires-Dist: plotly
